{
  "size": 10,
  "row": 10,
  "col": 10,
  "holes": [
    0,
    1,
    8,
    9,
    10,
    18,
    19,
    28,
    29,
    38,
    39,
    48,
    49,
    58,
    59
  ],
  "difficulty": "hard",
  "id": 666,
  "answer": [
    46,
    36,
    26,
    16,
    6,
    7,
    17,
    27,
    37,
    47,
    57,
    56,
    66,
    67,
    68,
    69,
    79,
    89,
    99,
    98,
    97,
    96,
    95,
    94,
    93,
    92,
    91,
    90,
    80,
    81,
    82,
    83,
    84,
    85,
    86,
    87,
    88,
    78,
    77,
    76,
    75,
    65,
    55,
    45,
    35,
    25,
    15,
    5,
    4,
    14,
    24,
    34,
    44,
    54,
    64,
    74,
    73,
    63,
    53,
    43,
    33,
    23,
    13,
    3,
    2,
    12,
    22,
    32,
    42,
    52,
    62,
    72,
    71,
    70,
    60,
    61,
    51,
    50,
    40,
    41,
    31,
    30,
    20,
    21,
    11
  ]
}