{
  "size": 8,
  "row": 8,
  "col": 8,
  "holes": [
    22,
    23,
    30,
    31,
    38,
    39,
    46,
    47,
    54,
    55
  ],
  "id": 538,
  "answer": [
    42,
    41,
    40,
    48,
    56,
    57,
    49,
    50,
    58,
    59,
    51,
    43,
    35,
    34,
    33,
    32,
    24,
    16,
    8,
    0,
    1,
    2,
    3,
    4,
    5,
    6,
    7,
    15,
    14,
    13,
    12,
    11,
    10,
    9,
    17,
    25,
    26,
    18,
    19,
    27,
    28,
    20,
    21,
    29,
    37,
    36,
    44,
    45,
    53,
    52,
    60,
    61,
    62,
    63
  ],
  "difficulty": "medium"
}