{
  "size": 8,
  "row": 8,
  "col": 8,
  "holes": [
    41,
    42,
    43,
    45,
    46,
    49,
    50,
    51
  ],
  "id": 217,
  "answer": [
    17,
    16,
    8,
    0,
    1,
    9,
    10,
    2,
    3,
    4,
    5,
    6,
    7,
    15,
    14,
    13,
    12,
    11,
    19,
    18,
    26,
    27,
    35,
    34,
    33,
    25,
    24,
    32,
    40,
    48,
    56,
    57,
    58,
    59,
    60,
    61,
    62,
    63,
    55,
    47,
    39,
    31,
    23,
    22,
    21,
    20,
    28,
    29,
    30,
    38,
    37,
    36,
    44,
    52,
    53,
    54
  ],
  "difficulty": "medium"
}