{
  "size": 8,
  "row": 8,
  "col": 8,
  "holes": [
    4,
    5,
    12,
    13,
    14
  ],
  "id": 124,
  "answer": [
    52,
    60,
    59,
    51,
    50,
    58,
    57,
    56,
    48,
    49,
    41,
    40,
    32,
    24,
    16,
    8,
    0,
    1,
    9,
    17,
    25,
    33,
    34,
    42,
    43,
    44,
    36,
    35,
    27,
    26,
    18,
    10,
    2,
    3,
    11,
    19,
    20,
    28,
    29,
    21,
    22,
    30,
    38,
    37,
    45,
    53,
    61,
    62,
    63,
    55,
    54,
    46,
    47,
    39,
    31,
    23,
    15,
    7,
    6
  ],
  "difficulty": "medium"
}