{
  "date": "2025-12-27",
  "name": "2025年12月28日数独",
  "level": "★★☆☆☆",
  "difficulty": "中等",
  "puzzle": [
    [
      6,
      4,
      9,
      0,
      0,
      0,
      3,
      2,
      1
    ],
    [
      1,
      0,
      7,
      0,
      9,
      6,
      0,
      4,
      8
    ],
    [
      5,
      0,
      0,
      2,
      0,
      1,
      0,
      7,
      0
    ],
    [
      9,
      1,
      0,
      0,
      0,
      3,
      0,
      0,
      0
    ],
    [
      3,
      8,
      6,
      9,
      7,
      4,
      0,
      0,
      2
    ],
    [
      0,
      0,
      2,
      0,
      1,
      5,
      8,
      0,
      9
    ],
    [
      7,
      0,
      0,
      0,
      3,
      0,
      0,
      9,
      5
    ],
    [
      8,
      0,
      0,
      0,
      0,
      0,
      0,
      0,
      0
    ],
    [
      0,
      0,
      4,
      1,
      6,
      0,
      7,
      0,
      3
    ]
  ],
  "emptyCells": 40
}