{
  "date": "2027-12-11",
  "name": "2027年12月12日数独",
  "level": "★☆☆☆☆",
  "difficulty": "简单",
  "puzzle": [
    [
      0,
      2,
      0,
      6,
      4,
      7,
      8,
      0,
      3
    ],
    [
      7,
      8,
      4,
      0,
      5,
      0,
      0,
      9,
      6
    ],
    [
      0,
      6,
      3,
      0,
      8,
      9,
      7,
      1,
      4
    ],
    [
      3,
      0,
      2,
      8,
      0,
      5,
      4,
      6,
      0
    ],
    [
      0,
      7,
      6,
      0,
      2,
      1,
      9,
      0,
      5
    ],
    [
      9,
      5,
      8,
      0,
      0,
      6,
      1,
      0,
      0
    ],
    [
      0,
      0,
      0,
      7,
      3,
      8,
      6,
      0,
      0
    ],
    [
      6,
      0,
      7,
      9,
      1,
      0,
      5,
      0,
      0
    ],
    [
      8,
      0,
      1,
      0,
      6,
      2,
      0,
      7,
      9
    ]
  ],
  "emptyCells": 30
}