{
  "date": "2030-06-28",
  "name": "2030年6月29日数独",
  "level": "★★★★★",
  "difficulty": "专家",
  "puzzle": [
    [
      4,
      0,
      0,
      7,
      0,
      3,
      1,
      0,
      0
    ],
    [
      0,
      0,
      0,
      0,
      0,
      0,
      7,
      0,
      2
    ],
    [
      6,
      0,
      3,
      5,
      0,
      0,
      0,
      0,
      0
    ],
    [
      8,
      0,
      0,
      4,
      0,
      0,
      6,
      0,
      0
    ],
    [
      0,
      0,
      0,
      0,
      0,
      0,
      0,
      0,
      9
    ],
    [
      0,
      0,
      0,
      0,
      0,
      9,
      3,
      4,
      0
    ],
    [
      0,
      0,
      9,
      0,
      0,
      0,
      8,
      0,
      0
    ],
    [
      0,
      0,
      0,
      0,
      0,
      0,
      0,
      7,
      0
    ],
    [
      0,
      0,
      5,
      8,
      6,
      1,
      0,
      0,
      0
    ]
  ],
  "emptyCells": 58
}