{
  "meta": {
    "tag": "收集需求",
    "count": 5,
    "generatedAt": "2026-03-29T14:57:05.948Z"
  },
  "articles": [
    {
      "id": "article-1774796225856",
      "filename": "需求跟踪矩阵.json",
      "title": "需求跟踪矩阵",
      "description": "",
      "category": "项目范围管理",
      "wordCount": 420,
      "updateTime": "2026-03-29T14:26:13.249Z",
      "order": 100
    },
    {
      "id": "article-1774796225843",
      "filename": "系统交互图.json",
      "title": "系统交互图",
      "description": "",
      "category": "项目范围管理",
      "wordCount": 115,
      "updateTime": "2026-03-29T14:26:13.247Z",
      "order": 101
    },
    {
      "id": "article-1774796225855",
      "filename": "需求文件.json",
      "title": "需求文件",
      "description": "",
      "category": "项目范围管理",
      "wordCount": 667,
      "updateTime": "2026-03-29T14:26:13.247Z",
      "order": 102
    },
    {
      "id": "article-1774796225836",
      "filename": "收集需求.json",
      "title": "收集需求",
      "description": "",
      "category": "项目范围管理",
      "wordCount": 409,
      "updateTime": "2026-03-29T14:26:13.246Z",
      "order": 103
    },
    {
      "id": "article-1774796225826",
      "filename": "原型法.json",
      "title": "原型法",
      "description": "",
      "category": "项目范围管理",
      "wordCount": 316,
      "updateTime": "2026-03-29T14:26:13.245Z",
      "order": 104
    }
  ]
}