{
  "meta": {
    "tag": "规划采购管理",
    "count": 9,
    "generatedAt": "2026-03-30T00:45:15.228Z"
  },
  "articles": [
    {
      "id": "article-1774831515073",
      "filename": "采购策略.json",
      "title": "采购策略",
      "description": "一旦完成自制或外购分析，并决定从项目外部渠道采购，就应制定一套采购策略。应该在采购策略中规定项目交付方法、具有法律约束力的协议类型，以及如何在采购阶段推动采购进展。",
      "category": "项目采购管理",
      "wordCount": 599,
      "updateTime": "2026-03-29T15:52:18.851Z",
      "order": 51
    },
    {
      "id": "article-1774831515073",
      "filename": "采购管理计划.json",
      "title": "采购管理计划",
      "description": "采购管理计划包含要在采购过程中开展的各种活动。",
      "category": "项目采购管理",
      "wordCount": 359,
      "updateTime": "2026-03-29T15:52:18.851Z",
      "order": 52
    },
    {
      "id": "article-1774831515073",
      "filename": "采购工作说明书.json",
      "title": "采购工作说明书",
      "description": "依据项目范围基准，为每次采购编制工作说明书（SOW），仅对将要包含在相关合同中的那一部分项目范围进行定义。",
      "category": "项目采购管理",
      "wordCount": 440,
      "updateTime": "2026-03-29T15:52:18.848Z",
      "order": 56
    },
    {
      "id": "article-1774831515067",
      "filename": "规划采购管理.json",
      "title": "规划采购管理",
      "description": "规划采购管理是记录项目采购决策、明确采购方法，及识别潜在卖方的过程。",
      "category": "项目采购管理",
      "wordCount": 572,
      "updateTime": "2026-03-29T15:52:18.830Z",
      "order": 83
    },
    {
      "id": "article-1774831515063",
      "filename": "自制或外购决策.json",
      "title": "自制或外购决策",
      "description": "通过自制或外购分析，做出某项特定工作最好由项目团队自己完成，还是需要从外部渠道采购的决策。",
      "category": "项目采购管理",
      "wordCount": 45,
      "updateTime": "2026-03-29T15:52:18.817Z",
      "order": 98
    },
    {
      "id": "article-1774831515057",
      "filename": "独立成本估算.json",
      "title": "独立成本估算",
      "description": "对于大型的采购，采购组织可以自行准备独立估算，或聘用外部专业估算师做出成本估算，并将其作为评价卖方报价的对照基准。",
      "category": "项目采购管理",
      "wordCount": 114,
      "updateTime": "2026-03-29T15:52:18.796Z",
      "order": 127
    },
    {
      "id": "article-1774831515051",
      "filename": "招标文件.json",
      "title": "招标文件",
      "description": "如果主要依据价格来选择卖方（如购买商业或标准产品时），通常就使用标书、投标或报价等术语；如果其他考虑因素（如技术能力或技术方法）至关重要，则通常使用建议书之类的术语。",
      "category": "项目采购管理",
      "wordCount": 562,
      "updateTime": "2026-03-29T15:52:18.775Z",
      "order": 157
    },
    {
      "id": "article-1774831515040",
      "filename": "供方选择标准.json",
      "title": "供方选择标准",
      "description": "在确定评估标准时，买方要努力确保选出的建议书将提供最佳质量的所需服务。供方选择标准可包括（但不限于）：",
      "category": "项目采购管理",
      "wordCount": 307,
      "updateTime": "2026-03-29T15:52:18.653Z",
      "order": 209
    },
    {
      "id": "article-1774831515040",
      "filename": "供方选择分析.json",
      "title": "供方选择分析",
      "description": "在确定选择方法前，有必要审查项目竞争性需求的优先级。由于竞争性选择方法可能要求卖方在事前投入大量时间和资源，因此，应该在采购文件中写明评估方法，让投标人了解将会被如何评估。常用的选择方法包括：",
      "category": "项目采购管理",
      "wordCount": 709,
      "updateTime": "2026-03-29T15:52:18.643Z",
      "order": 210
    }
  ]
}