{
  "id": "article-1774797037345",
  "filename": "变更请求.json",
  "title": "变更请求",
  "description": "",
  "category": "项目整合管理",
  "tags": [
    "执行过程组",
    "指导与管理项目工作"
  ],
  "wordCount": 362,
  "birthtime": "2026-03-29T14:58:37.465Z",
  "updateTime": "2026-03-29T14:58:37.466Z",
  "content": "\r\n变更请求是关于修改任何文件、可交付成果或基准的正式提议。  \r\n如果在开展项目工作时发现问题，就可提出变更请求，对项目政策或程序、项目或产品范围、项目成本或预算、项目进度计划、项目或产品结果的质量进行修改。  \r\n其他变更请求包括必要的预防措施或纠正措施，用来防止以后的不利后果。  \r\n任何项目相关方都可以提出变更请求，应该通过实施整体变更控制过程（见 4.6 节）对变更请求进行审查和处理。  \r\n变更请求源自项目内部或外部，是可选或由法律（合同）强制的。变更请求可能包括：\r\n\r\n- 纠正措施。为使项目工作绩效重新与项目管理计划一致，而进行的有目的的活动。\r\n- 预防措施。为确保项目工作的未来绩效符合项目管理计划，而进行的有目的的活动。\r\n- 缺陷补救。为了修正不一致产品或产品组件的有目的的活动。  \r\n\r\n更新。对正式受控的项目文件或计划等进行的变更，以反映修改或增加的意见或内容。"
}